ibrahimiq_qcmd-1.0.18.dist-info/licenses/LICENSE
qcmd_cli/__init__.py
qcmd_cli/__main__.py
qcmd_cli/post_install.py
qcmd_cli/qcmd.py
qcmd_cli/commands/__init__.py
qcmd_cli/commands/handler.py
qcmd_cli/config/__init__.py
qcmd_cli/config/constants.py
qcmd_cli/config/settings.py
qcmd_cli/core/__init__.py
qcmd_cli/core/command_generator.py
qcmd_cli/core/interactive_shell.py
qcmd_cli/log_analysis/__init__.py
qcmd_cli/log_analysis/analyzer.py
qcmd_cli/log_analysis/log_files.py
qcmd_cli/log_analysis/monitor.py
qcmd_cli/log_analysis/monitor_state.py
qcmd_cli/log_analysis/test_system.py
qcmd_cli/ui/__init__.py
qcmd_cli/ui/colors.py
qcmd_cli/ui/display.py
qcmd_cli/utils/__init__.py
qcmd_cli/utils/env_loader.py
qcmd_cli/utils/history.py
qcmd_cli/utils/ollama.py
qcmd_cli/utils/session.py
qcmd_cli/utils/system.py
ibrahimiq_qcmd-1.0.18.dist-info/METADATA
ibrahimiq_qcmd-1.0.18.dist-info/WHEEL
ibrahimiq_qcmd-1.0.18.dist-info/entry_points.txt
ibrahimiq_qcmd-1.0.18.dist-info/top_level.txt
ibrahimiq_qcmd-1.0.18.dist-info/RECORD
