Metadata-Version: 2.4
Name: ibrahimiq-qcmd
Version: 1.0.18
Summary: A command-line tool that generates shell commands using Qwen2.5-Coder via Ollama
Author-email: Ibrahim IQ <example@example.com>
License: MIT
Project-URL: Homepage, https://github.com/ibrahimiq/qcmd
Project-URL: Issues, https://github.com/ibrahimiq/qcmd/issues
Project-URL: Documentation, https://github.com/aledanee/qcmd/blob/main/qcmd-docs.html
Classifier: Development Status :: 5 - Production/Stable
Classifier: Environment :: Console
Classifier: Intended Audience :: Developers
Classifier: Intended Audience :: System Administrators
Classifier: Programming Language :: Python :: 3
Classifier: Programming Language :: Python :: 3.8
Classifier: Programming Language :: Python :: 3.9
Classifier: Programming Language :: Python :: 3.10
Classifier: Programming Language :: Python :: 3.11
Classifier: Topic :: System :: Shells
Classifier: Topic :: Utilities
Requires-Python: >=3.8
License-File: LICENSE
Requires-Dist: requests>=2.25.0
Requires-Dist: pyfiglet>=0.8.0
Dynamic: license-file
